fourmat/__init__.py
fourmat/lint.py
fourmat/assets/.flake8
fourmat/assets/pyproject.toml
fourmat-2.0.0.dist-info/licenses/LICENSE
fourmat-2.0.0.dist-info/METADATA
fourmat-2.0.0.dist-info/WHEEL
fourmat-2.0.0.dist-info/entry_points.txt
fourmat-2.0.0.dist-info/top_level.txt
fourmat-2.0.0.dist-info/RECORD
